LICENSE
MANIFEST.in
requirements.txt
setup.py
Flask_FileUpload.egg-info/PKG-INFO
Flask_FileUpload.egg-info/SOURCES.txt
Flask_FileUpload.egg-info/dependency_links.txt
Flask_FileUpload.egg-info/not-zip-safe
Flask_FileUpload.egg-info/requires.txt
Flask_FileUpload.egg-info/top_level.txt
flask_fileupload/__init__.py
flask_fileupload/engine.py
flask_fileupload/forms.py
flask_fileupload/storage.py
flask_fileupload/views.py
flask_fileupload/static/css/zoom.css
flask_fileupload/templates/fileupload/base.html
flask_fileupload/templates/fileupload/upload.html
test/__init__.py
test/test_permission.py
test/test_storage.py